PTS/__init__.py
PTS/core.py
PTS/errors.py
PTS/size.py
PTS-1.4.8.dist-info/LICENSE
PTS-1.4.8.dist-info/METADATA
PTS-1.4.8.dist-info/WHEEL
PTS-1.4.8.dist-info/top_level.txt
PTS-1.4.8.dist-info/RECORD
