Metadata-Version: 2.1
Name: PTS
Version: 1.4.8
Summary: PIL Text Scaler
Home-page: https://github.com/TheElementalOfDestruction/pts
Author: Destiny Peterson (The Elemental of Destruction)
Author-email: arceusthe@gmail.com
License: GPL
Download-URL: https://github.com/TheElementalOfDestruction/pts/archives/master
Platform: UNKNOWN
License-File: LICENSE
Requires-Dist: pillow (>=5.4.1)
